openstack_member_spammer_estimator/__init__.py
openstack_member_spammer_estimator/data_frame_column_extracter.py
openstack_member_spammer_estimator/dbutils.py
openstack_member_spammer_estimator/html_preprocessor.py
openstack_member_spammer_estimator/member_spammer_estimator_build.py
openstack_member_spammer_estimator/member_spammer_estimator_process.py
tests/__init__.py
tests/test_estimator.py
openstack_member_spammer_estimator-1.0.2.dist-info/METADATA
openstack_member_spammer_estimator-1.0.2.dist-info/WHEEL
openstack_member_spammer_estimator-1.0.2.dist-info/top_level.txt
openstack_member_spammer_estimator-1.0.2.dist-info/RECORD
