Metadata-Version: 2.1
Name: openstack-member-spammer-estimator
Version: 1.0.2
Summary: Member Spam detector
Home-page: https://github.com/OpenStackWeb/openstack_member_spammer_estimator
Author: Sebastian Marcet
Author-email: smarcet@gmail.com
License: UNKNOWN
Platform: UNKNOWN
Classifier: Programming Language :: Python :: 3
Classifier: License :: OSI Approved :: MIT License
Classifier: Operating System :: OS Independent
Requires-Python: >=3.5
